openconnecter/__main__.py
openconnecter-0.0.1.dist-info/entry_points.txt
openconnecter-0.0.1.dist-info/WHEEL
openconnecter-0.0.1.dist-info/METADATA
openconnecter-0.0.1.dist-info/RECORD
