Metadata-Version: 2.1
Name: openconnecter
Version: 0.0.1
Summary: Wrapper for initiating an openconnect session
Home-page: https://github.com/kamyabzad/openconnecter
License: MIT
Keywords: openconnect,vpn,automation
Author: Kamyab Taghizadeh
Author-email: kamyab.zad@gmail.com
Requires-Python: >=3.6,<4.0
Classifier: License :: OSI Approved :: MIT License
Classifier: Programming Language :: Python :: 3
Classifier: Programming Language :: Python :: 3.6
Classifier: Programming Language :: Python :: 3.7
Classifier: Programming Language :: Python :: 3.8
Classifier: Programming Language :: Python :: 3.9
Requires-Dist: pyotp (>=2.6.0,<3.0.0)
Project-URL: Repository, https://github.com/kamyabzad/openconnecter
